udata_ldap/__init__.py
udata_ldap/commands.py
udata_ldap/forms.py
udata_ldap/kerberos.py
udata_ldap/ldap.py
udata_ldap/settings.py
udata_ldap/utils.py
udata_ldap/views.py
udata_ldap/templates/ldap/login.html
udata_ldap/templates/ldap/negociate.html
udata_ldap/translations/fr/LC_MESSAGES/udata-ldap.mo
udata_ldap/translations/fr/LC_MESSAGES/udata-ldap.po
udata_ldap-0.3.5.dist-info/LICENSE
udata_ldap-0.3.5.dist-info/METADATA
udata_ldap-0.3.5.dist-info/WHEEL
udata_ldap-0.3.5.dist-info/entry_points.txt
udata_ldap-0.3.5.dist-info/top_level.txt
udata_ldap-0.3.5.dist-info/RECORD
