Metadata-Version: 2.1
Name: udata-ldap
Version: 0.3.5
Summary: LDAP authentification for udata with optional Kerberos suppport.
Home-page: https://github.com/opendatateam/udata-ldap
Author: Open Data Team
Author-email: contact@opendata.team
License: MIT
Keywords: udata LDAP
Platform: UNKNOWN
Classifier: Development Status :: 3 - Alpha
Classifier: Programming Language :: Python
Classifier: Environment :: Web Environment
Classifier: Operating System :: OS Independent
Classifier: Intended Audience :: Developers
Classifier: Topic :: System :: Software Distribution
Classifier: Programming Language :: Python
Classifier: Programming Language :: Python :: 2
Classifier: Programming Language :: Python :: 2.7
Classifier: Topic :: Software Development :: Libraries :: Python Modules
Requires-Python: ==2.7.*
Requires-Dist: udata (>=1.4.0.dev)
Requires-Dist: flask-ldap3-login (==0.9.15)
Provides-Extra: kerberos
Requires-Dist: gssapi (==1.5.0) ; extra == 'kerberos'
Provides-Extra: test
Requires-Dist: httpretty (==0.9.5) ; extra == 'test'
Requires-Dist: mock (==2.0.0) ; extra == 'test'
Requires-Dist: pytest (==3.10.0) ; extra == 'test'
Requires-Dist: pytest-flask (==0.14.0) ; extra == 'test'
Requires-Dist: pytest-mock (==1.10.0) ; extra == 'test'
Requires-Dist: pytest-sugar (==0.9.2) ; extra == 'test'
